libertymetric/__init__.py
libertymetric/classLiberty.py
libertymetric-0.1.4.dist-info/LICENSE
libertymetric-0.1.4.dist-info/METADATA
libertymetric-0.1.4.dist-info/WHEEL
libertymetric-0.1.4.dist-info/top_level.txt
libertymetric-0.1.4.dist-info/RECORD
