Metadata-Version: 2.1
Name: libertymetric
Version: 0.1.4
Summary: Liberty Metric Utility
Home-page: https://github.com/dipsci/liberty
Author: hockchen
Author-email: hock.chen@dipsci.com
License: UNKNOWN
Keywords: liberty,metric,timing,EDA,physical design
Platform: UNKNOWN
Classifier: Programming Language :: Python :: 3
Classifier: License :: OSI Approved :: MIT License
